sanmu/sender.cpython-312-darwin.so
sanmu/cmd.cpython-312-darwin.so
sanmu/settings.cpython-312-darwin.so
sanmu/__init__.cpython-312-darwin.so
sanmu/plugin.cpython-312-darwin.so
sanmu/exchange.cpython-312-darwin.so
sanmu/runner.cpython-312-darwin.so
sanmu/kdt_utils.cpython-312-darwin.so
sanmu/_custom.cpython-312-darwin.so
sanmu/_plugin.cpython-312-darwin.so
sanmu/__main__.cpython-312-darwin.so
sanmu/files.cpython-312-darwin.so
sanmu/sanmu_steps.schema.yaml
sanmu/assertion.cpython-312-darwin.so
sanmu/kdt.cpython-312-darwin.so
sanmu/file/pytest.ini.txt
sanmu/file/template.xlsx
sanmu-0.6.0.dist-info/RECORD
sanmu-0.6.0.dist-info/WHEEL
sanmu-0.6.0.dist-info/entry_points.txt
sanmu-0.6.0.dist-info/METADATA
