Metadata-Version: 2.1
Name: sanmu
Version: 0.6.0
Summary: 基于pytest实现低代码自动化测试框架，支持web测试、app测试、api测试。只需要编辑xlsx文件或yaml即可完成测试。
Author: dongfangtianyu
Requires-Python: <3.13,>=3.12
Requires-Dist: Pillow~=10.1.0
Requires-Dist: allure-pytest<2.14,>=2.13.5
Requires-Dist: click~=8.1.7
Requires-Dist: email-validator~=2.0
Requires-Dist: genson~=1.2.2
Requires-Dist: httpx~=0.25.0
Requires-Dist: iniconfig~=2.0.0
Requires-Dist: jsonpath~=0.82
Requires-Dist: jsonschema~=4.21.0
Requires-Dist: pydantic-settings~=2.0.2
Requires-Dist: pydantic<3.0,>=2.1.1
Requires-Dist: pyjwt[crypto]>=2.8.0
Requires-Dist: pymysql>=1.1.1
Requires-Dist: pytest-result-log~=1.2.1
Requires-Dist: pytest-yaml-sanmu==1.0.0
Requires-Dist: pytest~=8.2
Requires-Dist: responses-validator>=0.1.6
Requires-Dist: webdriver-helper
Project-URL: Homepage, https://github.com/dongfangtianyu/sanmu
